mlx/traceability/__init__.py
mlx/traceability/__traceability_version__.py
mlx/traceability/callback_utils.py
mlx/traceability/traceability.py
mlx/traceability/traceability_exception.py
mlx/traceability/traceable_attribute.py
mlx/traceability/traceable_base_class.py
mlx/traceability/traceable_base_directive.py
mlx/traceability/traceable_base_node.py
mlx/traceability/traceable_collection.py
mlx/traceability/traceable_item.py
mlx/traceability/assets/traceability-11.8.2.min.js
mlx/traceability/directives/__init__.py
mlx/traceability/directives/attribute_link_directive.py
mlx/traceability/directives/attribute_sort_directive.py
mlx/traceability/directives/checkbox_result_directive.py
mlx/traceability/directives/checklist_item_directive.py
mlx/traceability/directives/item_2d_matrix_directive.py
mlx/traceability/directives/item_attribute_directive.py
mlx/traceability/directives/item_attributes_matrix_directive.py
mlx/traceability/directives/item_directive.py
mlx/traceability/directives/item_link_directive.py
mlx/traceability/directives/item_list_directive.py
mlx/traceability/directives/item_matrix_directive.py
mlx/traceability/directives/item_pie_chart_directive.py
mlx/traceability/directives/item_relink_directive.py
mlx/traceability/directives/item_tree_directive.py
mlx_traceability-11.8.2.dist-info/licenses/LICENSE.txt
mlx_traceability-11.8.2.dist-info/METADATA
mlx_traceability-11.8.2.dist-info/WHEEL
mlx_traceability-11.8.2.dist-info/top_level.txt
mlx_traceability-11.8.2.dist-info/RECORD
