Metadata-Version: 2.4
Name: mlx.traceability
Version: 11.8.2
Summary: Sphinx traceability extension (Melexis fork)
Home-page: https://github.com/melexis/sphinx-traceability-extension
Author: Melexis
Author-email: jce@melexis.com
License: GPL-3.0
Project-URL: Documentation, https://melexis.github.io/sphinx-traceability-extension
Project-URL: Source, https://github.com/melexis/sphinx-traceability-extension
Project-URL: Tracker, https://github.com/melexis/sphinx-traceability-extension/issues
Keywords: traceability,requirements engineering,requirements management,software engineering,systems engineering,sphinx,requirements,ASPICE,ISO26262,ASIL
Platform: any
Classifier: Development Status :: 5 - Production/Stable
Classifier: Environment :: Console
Classifier: Environment :: Web Environment
Classifier: Framework :: Sphinx :: Extension
Classifier: Intended Audience :: Developers
Classifier: Operating System :: OS Independent
Classifier: Programming Language :: Python
Classifier: Programming Language :: Python :: 3.9
Classifier: Programming Language :: Python :: 3.10
Classifier: Programming Language :: Python :: 3.11
Classifier: Programming Language :: Python :: 3.12
Classifier: Topic :: Documentation
Classifier: Topic :: Documentation :: Sphinx
Classifier: Topic :: Utilities
Requires-Python: >=3.8
License-File: LICENSE.txt
Requires-Dist: Sphinx<9.0,>=7.4
Requires-Dist: sphinxcontrib-jquery!=3.0.0,>=2.0.0
Requires-Dist: docutils
Requires-Dist: matplotlib<4.0
Requires-Dist: natsort
Requires-Dist: python-decouple
Requires-Dist: requests
Dynamic: author
Dynamic: author-email
Dynamic: classifier
Dynamic: description
Dynamic: description-content-type
Dynamic: home-page
Dynamic: keywords
Dynamic: license
Dynamic: license-file
Dynamic: platform
Dynamic: project-url
Dynamic: requires-dist
Dynamic: requires-python
Dynamic: summary
